setup.cfg
setup.py
auto_api_client/__init__.py
auto_api_client/exceptions.py
auto_api_client.egg-info/PKG-INFO
auto_api_client.egg-info/SOURCES.txt
auto_api_client.egg-info/dependency_links.txt
auto_api_client.egg-info/entry_points.txt
auto_api_client.egg-info/not-zip-safe
auto_api_client.egg-info/requires.txt
auto_api_client.egg-info/top_level.txt