Metadata-Version: 1.1
Name: auto-api-client
Version: 0.0.1
Summary: Automatic API REST from Python
Home-page: https://github.com/fvalverd/AutoApi-Client-Python
Author: Felipe Valverde Campos
Author-email: felipe.valverde.campos@gmail.com
License: MIT
Download-URL: https://github.com/fvalverd/AutoApi-client-Python/tarball/0.0.1
Keywords: api rest authentication automatic web json
Platform: UNKNOWN
Classifier: Environment :: Web Environment
Classifier: Intended Audience :: Developers
Classifier: License :: OSI Approved :: MIT License
Classifier: Operating System :: POSIX
Classifier: Programming Language :: Python
Classifier: Topic :: Internet :: WWW/HTTP :: Dynamic Content
Classifier: Topic :: Software Development :: Libraries :: Python Modules
